dash_markdown_editor/MdxEditor.py
dash_markdown_editor/__init__.py
dash_markdown_editor/_imports_.py
dash_markdown_editor/dash_markdown_editor.min.js
dash_markdown_editor/dash_markdown_editor.min.js.map
dash_markdown_editor/metadata.json
dash_markdown_editor/package-info.json
dash_markdown_editor-0.0.1.dist-info/LICENSE
dash_markdown_editor-0.0.1.dist-info/METADATA
dash_markdown_editor-0.0.1.dist-info/WHEEL
dash_markdown_editor-0.0.1.dist-info/top_level.txt
dash_markdown_editor-0.0.1.dist-info/RECORD
