Metadata-Version: 2.1
Name: dash_markdown_editor
Version: 0.0.1
Summary: Package with open-source markdown editors for Dash.
Author: Jose Gómez Gadea <josegomezgadea@gmail.com>
License: MIT
Classifier: Framework :: Dash
License-File: LICENSE
